[
    {
        "record": {
            "osti_id": "1488485",
            "accession_num": "88435/dsp01z316q451j",
            "product_nos": "None",
            "title": "Toward fusion plasma scenario planning for NSTX-U using machine-learning-accelerated models",
            "contract_nos": "AC02-09CH11466",
            "other_identifying_nos": null,
            "doi": "10.11578/1488485",
            "doi_status": "PENDING",
            "status": "SUCCESS",
            "status_message": null,
            "@status": "UPDATED"
        }
    },
    {
        "record": {
            "osti_id": "1488485",
            "accession_num": "88435/dsp01z316q451j",
            "product_nos": "None",
            "title": "Toward fusion plasma scenario planning for NSTX-U using machine-learning-accelerated models",
            "contract_nos": "AC02-09CH11466",
            "other_identifying_nos": null,
            "doi": "10.11578/1488485",
            "doi_status": "PENDING",
            "status": "SUCCESS",
            "status_message": null,
            "@status": "UPDATED"
        }
    },
    {
        "record": {
            "osti_id": "1488485",
            "accession_num": "88435/dsp01z316q451j",
            "product_nos": "None",
            "title": "Toward fusion plasma scenario planning for NSTX-U using machine-learning-accelerated models",
            "contract_nos": "AC02-09CH11466",
            "other_identifying_nos": null,
            "doi": "10.11578/1488485",
            "doi_status": "PENDING",
            "status": "SUCCESS",
            "status_message": null,
            "@status": "UPDATED"
        }
    },
    {
        "record": {
            "osti_id": "1488485",
            "accession_num": "88435/dsp01z316q451j",
            "product_nos": "None",
            "title": "Toward fusion plasma scenario planning for NSTX-U using machine-learning-accelerated models",
            "contract_nos": "AC02-09CH11466",
            "other_identifying_nos": null,
            "doi": "10.11578/1488485",
            "doi_status": "PENDING",
            "status": "SUCCESS",
            "status_message": null,
            "@status": "UPDATED"
        }
    },
    {
        "record": {
            "osti_id": "1488485",
            "accession_num": "88435/dsp01z316q451j",
            "product_nos": "None",
            "title": "Toward fusion plasma scenario planning for NSTX-U using machine-learning-accelerated models",
            "contract_nos": "AC02-09CH11466",
            "other_identifying_nos": null,
            "doi": "10.11578/1488485",
            "doi_status": "PENDING",
            "status": "SUCCESS",
            "status_message": null,
            "@status": "UPDATED"
        }
    },
    {
        "record": {
            "osti_id": "1488485",
            "accession_num": "88435/dsp01z316q451j",
            "product_nos": "None",
            "title": "Toward fusion plasma scenario planning for NSTX-U using machine-learning-accelerated models",
            "contract_nos": "AC02-09CH11466",
            "other_identifying_nos": null,
            "doi": "10.11578/1488485",
            "doi_status": "PENDING",
            "status": "SUCCESS",
            "status_message": null,
            "@status": "UPDATED"
        }
    },
    {
        "record": {
            "osti_id": "1488485",
            "accession_num": "88435/dsp01z316q451j",
            "product_nos": "None",
            "title": "Toward fusion plasma scenario planning for NSTX-U using machine-learning-accelerated models",
            "contract_nos": "AC02-09CH11466",
            "other_identifying_nos": null,
            "doi": "10.11578/1488485",
            "doi_status": "PENDING",
            "status": "SUCCESS",
            "status_message": null,
            "@status": "UPDATED"
        }
    }
]